lfsr/lfsr.v
module lfsr(

  input wire rst,
  input wire clk,
  input wire enable,
  output wire [31:0]out,
  output wire [7:0]out_lb,
  input wire [31:0]init_reg
);

reg [31:0]shift_reg;
assign out = shift_reg;
assign out_lb = shift_reg[7:0];
wire next_bit;
assign next_bit = 
  shift_reg[31] ^
  shift_reg[30] ^
  shift_reg[29] ^
  shift_reg[27] ^
  shift_reg[25] ^
  shift_reg[ 0];

always @(posedge clk or posedge rst)
  if(rst)
    //shift_reg <= 32'h974CA351;
	shift_reg <= init_reg;
  else
  if(enable)
    shift_reg <= { next_bit, shift_reg[31:1] };

endmodule

lfsr/tlfsr.v
module tlfsr;

reg clk;
reg rst;
reg en;
wire [31:0]wrandom1;
wire [7:0]wrandom_lb1;

wire [31:0]wrandom2;
wire [7:0]wrandom_lb2;

lfsr u_lfsr1(
  rst,
  clk,
  en,
  wrandom1,
  wrandom_lb1,
  32'h974CA351
  );
  
  lfsr u_lfsr2(
  rst,
  clk,
  en,
  wrandom2,
  wrandom_lb2,
  32'h5829487A
  );
  
  always
	#1 clk  = ~clk;
  
initial
begin
  $dumpfile("out.vcd");
  $dumpvars(0,tlfsr);
  clk <= 0;
  #10;
  rst <= 1'b1;
  #5 rst <= 1'b0;
  #10;
  en <= 1'b1;
  #100;
  $finish;
end

endmodule

lfsr/out.vcd
$date
	Wed Jun 07 14:46:38 2017
$end
$version
	Icarus Verilog
$end
$timescale
	1s
$end
$scope module tlfsr $end
$var wire 8 ! wrandom_lb2 [7:0] $end
$var wire 8 " wrandom_lb1 [7:0] $end
$var wire 32 # wrandom2 [31:0] $end
$var wire 32 $ wrandom1 [31:0] $end
$var reg 1 % clk $end
$var reg 1 & en $end
$var reg 1 ' rst $end
$scope module u_lfsr1 $end
$var wire 1 % clk $end
$var wire 1 & enable $end
$var wire 32 ( init_reg [31:0] $end
$var wire 1 ) next_bit $end
$var wire 32 * out [31:0] $end
$var wire 1 ' rst $end
$var wire 8 + out_lb [7:0] $end
$var reg 32 , shift_reg [31:0] $end
$upscope $end
$scope module u_lfsr2 $end
$var wire 1 % clk $end
$var wire 1 & enable $end
$var wire 32 - init_reg [31:0] $end
$var wire 1 . next_bit $end
$var wire 32 / out [31:0] $end
$var wire 1 ' rst $end
$var wire 8 0 out_lb [7:0] $end
$var reg 32 1 shift_reg [31:0] $end
$upscope $end
$upscope $end
$enddefinitions $end
#0
$dumpvars
bx 1
bx 0
bx /
x.
b1011000001010010100100001111010 -
bx ,
bx +
bx *
x)
b10010111010011001010001101010001 (
x'
x&
0%
bx $
bx #
bx "
bx !
$end
#1
1%
#2
0%
#3
1%
#4
0%
#5
1%
#6
0%
#7
1%
#8
0%
#9
1%
#10
0.
1)
b1111010 !
b1111010 0
b1010001 "
b1010001 +
b1011000001010010100100001111010 #
b1011000001010010100100001111010 /
b1011000001010010100100001111010 1
b10010111010011001010001101010001 $
b10010111010011001010001101010001 *
b10010111010011001010001101010001 ,
1'
0%
#11
1%
#12
0%
#13
1%
#14
0%
#15
0'
1%
#16
0%
#17
1%
#18
0%
#19
1%
#20
0%
#21
1%
#22
0%
#23
1%
#24
0%
#25
1&
1%
#26
0%
#27
0)
1.
b10101000 "
b10101000 +
b111101 !
b111101 0
b11001011101001100101000110101000 $
b11001011101001100101000110101000 *
b11001011101001100101000110101000 ,
b101100000101001010010000111101 #
b101100000101001010010000111101 /
b101100000101001010010000111101 1
1%
#28
0%
#29
0)
0.
b11110 !
b11110 0
b11010100 "
b11010100 +
b10010110000010100101001000011110 #
b10010110000010100101001000011110 /
b10010110000010100101001000011110 1
b1100101110100110010100011010100 $
b1100101110100110010100011010100 *
b1100101110100110010100011010100 ,
1%
#30
0%
#31
0)
0.
b1101010 "
b1101010 +
b1111 !
b1111 0
b110010111010011001010001101010 $
b110010111010011001010001101010 *
b110010111010011001010001101010 ,
b1001011000001010010100100001111 #
b1001011000001010010100100001111 /
b1001011000001010010100100001111 1
1%
#32
0%
#33
0.
0)
b10000111 !
b10000111 0
b110101 "
b110101 +
b100101100000101001010010000111 #
b100101100000101001010010000111 /
b100101100000101001010010000111 1
b11001011101001100101000110101 $
b11001011101001100101000110101 *
b11001011101001100101000110101 ,
1%
#34
0%
#35
0.
1)
b11010 "
b11010 +
b1000011 !
b1000011 0
b1100101110100110010100011010 $
b1100101110100110010100011010 *
b1100101110100110010100011010 ,
b10010110000010100101001000011 #
b10010110000010100101001000011 /
b10010110000010100101001000011 1
1%
#36
0%
#37
0.
1)
b100001 !
b100001 0
b10001101 "
b10001101 +
b1001011000001010010100100001 #
b1001011000001010010100100001 /
b1001011000001010010100100001 1
b10000110010111010011001010001101 $
b10000110010111010011001010001101 *
b10000110010111010011001010001101 ,
1%
#38
0%
#39
1)
0.
b1000110 "
b1000110 +
b10010000 !
b10010000 0
b11000011001011101001100101000110 $
b11000011001011101001100101000110 *
b11000011001011101001100101000110 ,
b100101100000101001010010000 #
b100101100000101001010010000 /
b100101100000101001010010000 1
1%
#40
0%
#41
1.
0)
b1001000 !
b1001000 0
b10100011 "
b10100011 +
b10010110000010100101001000 #
b10010110000010100101001000 /
b10010110000010100101001000 1
b11100001100101110100110010100011 $
b11100001100101110100110010100011 *
b11100001100101110100110010100011 ,
1%
#42
0%
#43
1)
1.
b1010001 "
b1010001 +
b10100100 !
b10100100 0
b1110000110010111010011001010001 $
b1110000110010111010011001010001 *
b1110000110010111010011001010001 ,
b10000001001011000001010010100100 #
b10000001001011000001010010100100 /
b10000001001011000001010010100100 1
1%
#44
0%
#45
0.
1)
b1010010 !
b1010010 0
b101000 "
b101000 +
b11000000100101100000101001010010 #
b11000000100101100000101001010010 /
b11000000100101100000101001010010 1
b10111000011001011101001100101000 $
b10111000011001011101001100101000 *
b10111000011001011101001100101000 ,
1%
#46
0%
#47
1)
1.
b10010100 "
b10010100 +
b101001 !
b101001 0
b11011100001100101110100110010100 $
b11011100001100101110100110010100 *
b11011100001100101110100110010100 ,
b1100000010010110000010100101001 #
b1100000010010110000010100101001 /
b1100000010010110000010100101001 1
1%
#48
0%
#49
1)
0.
b10010100 !
b10010100 0
b11001010 "
b11001010 +
b10110000001001011000001010010100 #
b10110000001001011000001010010100 /
b10110000001001011000001010010100 1
b11101110000110010111010011001010 $
b11101110000110010111010011001010 *
b11101110000110010111010011001010 ,
1%
#50
0%
#51
0.
1)
b1100101 "
b1100101 +
b1001010 !
b1001010 0
b11110111000011001011101001100101 $
b11110111000011001011101001100101 *
b11110111000011001011101001100101 ,
b1011000000100101100000101001010 #
b1011000000100101100000101001010 /
b1011000000100101100000101001010 1
1%
#52
0%
#53
1.
1)
b10100101 !
b10100101 0
b110010 "
b110010 +
b101100000010010110000010100101 #
b101100000010010110000010100101 /
b101100000010010110000010100101 1
b11111011100001100101110100110010 $
b11111011100001100101110100110010 *
b11111011100001100101110100110010 ,
1%
#54
0%
#55
1)
0.
b10011001 "
b10011001 +
b1010010 !
b1010010 0
b11111101110000110010111010011001 $
b11111101110000110010111010011001 *
b11111101110000110010111010011001 ,
b10010110000001001011000001010010 #
b10010110000001001011000001010010 /
b10010110000001001011000001010010 1
1%
#56
0%
#57
0.
1)
b101001 !
b101001 0
b1001100 "
b1001100 +
b1001011000000100101100000101001 #
b1001011000000100101100000101001 /
b1001011000000100101100000101001 1
b11111110111000011001011101001100 $
b11111110111000011001011101001100 *
b11111110111000011001011101001100 ,
1%
#58
0%
#59
1.
b10100110 "
b10100110 +
b10100 !
b10100 0
b11111111011100001100101110100110 $
b11111111011100001100101110100110 *
b11111111011100001100101110100110 ,
b100101100000010010110000010100 #
b100101100000010010110000010100 /
b100101100000010010110000010100 1
1%
#60
0%
#61
0.
0)
b1010 !
b1010 0
b11010011 "
b11010011 +
b10010010110000001001011000001010 #
b10010010110000001001011000001010 /
b10010010110000001001011000001010 1
b11111111101110000110010111010011 $
b11111111101110000110010111010011 *
b11111111101110000110010111010011 ,
1%
#62
0%
#63
1)
1.
b11101001 "
b11101001 +
b101 !
b101 0
b1111111110111000011001011101001 $
b1111111110111000011001011101001 *
b1111111110111000011001011101001 ,
b1001001011000000100101100000101 #
b1001001011000000100101100000101 /
b1001001011000000100101100000101 1
1%
#64
0%
#65
0.
0)
b10000010 !
b10000010 0
b1110100 "
b1110100 +
b10100100101100000010010110000010 #
b10100100101100000010010110000010 /
b10100100101100000010010110000010 1
b10111111111011100001100101110100 $
b10111111111011100001100101110100 *
b10111111111011100001100101110100 ,
1%
#66
0%
#67
1)
1.
b10111010 "
b10111010 +
b11000001 !
b11000001 0
b1011111111101110000110010111010 $
b1011111111101110000110010111010 *
b1011111111101110000110010111010 ,
b1010010010110000001001011000001 #
b1010010010110000001001011000001 /
b1010010010110000001001011000001 1
1%
#68
0%
#69
1.
1)
b1100000 !
b1100000 0
b1011101 "
b1011101 +
b10101001001011000000100101100000 #
b10101001001011000000100101100000 /
b10101001001011000000100101100000 1
b10101111111110111000011001011101 $
b10101111111110111000011001011101 *
b10101111111110111000011001011101 ,
1%
#70
0%
#71
0.
1)
b101110 "
b101110 +
b10110000 !
b10110000 0
b11010111111111011100001100101110 $
b11010111111111011100001100101110 *
b11010111111111011100001100101110 ,
b11010100100101100000010010110000 #
b11010100100101100000010010110000 /
b11010100100101100000010010110000 1
1%
#72
0%
#73
0.
0)
b1011000 !
b1011000 0
b10010111 "
b10010111 +
b1101010010010110000001001011000 #
b1101010010010110000001001011000 /
b1101010010010110000001001011000 1
b11101011111111101110000110010111 $
b11101011111111101110000110010111 *
b11101011111111101110000110010111 ,
1%
#74
0%
#75
1)
1.
b11001011 "
b11001011 +
b101100 !
b101100 0
b1110101111111110111000011001011 $
b1110101111111110111000011001011 *
b1110101111111110111000011001011 ,
b110101001001011000000100101100 #
b110101001001011000000100101100 /
b110101001001011000000100101100 1
1%
#76
0%
#77
1.
1)
b10010110 !
b10010110 0
b1100101 "
b1100101 +
b10011010100100101100000010010110 #
b10011010100100101100000010010110 /
b10011010100100101100000010010110 1
b10111010111111111011100001100101 $
b10111010111111111011100001100101 *
b10111010111111111011100001100101 ,
1%
#78
0%
#79
1)
0.
b110010 "
b110010 +
b1001011 !
b1001011 0
b11011101011111111101110000110010 $
b11011101011111111101110000110010 *
b11011101011111111101110000110010 ,
b11001101010010010110000001001011 #
b11001101010010010110000001001011 /
b11001101010010010110000001001011 1
1%
#80
0%
#81
0.
0)
b100101 !
b100101 0
b11001 "
b11001 +
b1100110101001001011000000100101 #
b1100110101001001011000000100101 /
b1100110101001001011000000100101 1
b11101110101111111110111000011001 $
b11101110101111111110111000011001 *
b11101110101111111110111000011001 ,
1%
#82
0%
#83
1)
0.
b1100 "
b1100 +
b10010 !
b10010 0
b1110111010111111111011100001100 $
b1110111010111111111011100001100 *
b1110111010111111111011100001100 ,
b110011010100100101100000010010 #
b110011010100100101100000010010 /
b110011010100100101100000010010 1
1%
#84
0%
#85
0)
0.
b1001 !
b1001 0
b10000110 "
b10000110 +
b11001101010010010110000001001 #
b11001101010010010110000001001 /
b11001101010010010110000001001 1
b10111011101011111111101110000110 $
b10111011101011111111101110000110 *
b10111011101011111111101110000110 ,
1%
#86
0%
#87
1)
1.
b11000011 "
b11000011 +
b100 !
b100 0
b1011101110101111111110111000011 $
b1011101110101111111110111000011 *
b1011101110101111111110111000011 ,
b1100110101001001011000000100 #
b1100110101001001011000000100 /
b1100110101001001011000000100 1
1%
#88
0%
#89
0.
1)
b10 !
b10 0
b11100001 "
b11100001 +
b10000110011010100100101100000010 #
b10000110011010100100101100000010 /
b10000110011010100100101100000010 1
b10101110111010111111111011100001 $
b10101110111010111111111011100001 *
b10101110111010111111111011100001 ,
1%
#90
0%
#91
1)
1.
b1110000 "
b1110000 +
b10000001 !
b10000001 0
b11010111011101011111111101110000 $
b11010111011101011111111101110000 *
b11010111011101011111111101110000 ,
b1000011001101010010010110000001 #
b1000011001101010010010110000001 /
b1000011001101010010010110000001 1
1%
#92
0%
#93
1)
0.
b11000000 !
b11000000 0
b10111000 "
b10111000 +
b10100001100110101001001011000000 #
b10100001100110101001001011000000 /
b10100001100110101001001011000000 1
b11101011101110101111111110111000 $
b11101011101110101111111110111000 *
b11101011101110101111111110111000 ,
1%
#94
0%
#95
1.
1)
b11011100 "
b11011100 +
b1100000 !
b1100000 0
b11110101110111010111111111011100 $
b11110101110111010111111111011100 *
b11110101110111010111111111011100 ,
b1010000110011010100100101100000 #
b1010000110011010100100101100000 /
b1010000110011010100100101100000 1
1%
#96
0%
#97
1.
1)
b10110000 !
b10110000 0
b11101110 "
b11101110 +
b10101000011001101010010010110000 #
b10101000011001101010010010110000 /
b10101000011001101010010010110000 1
b11111010111011101011111111101110 $
b11111010111011101011111111101110 *
b11111010111011101011111111101110 ,
1%
#98
0%
#99
0.
1)
b11110111 "
b11110111 +
b1011000 !
b1011000 0
b11111101011101110101111111110111 $
b11111101011101110101111111110111 *
b11111101011101110101111111110111 ,
b11010100001100110101001001011000 #
b11010100001100110101001001011000 /
b11010100001100110101001001011000 1
1%
#100
0%
#101
0.
0)
b101100 !
b101100 0
b11111011 "
b11111011 +
b1101010000110011010100100101100 #
b1101010000110011010100100101100 /
b1101010000110011010100100101100 1
b11111110101110111010111111111011 $
b11111110101110111010111111111011 *
b11111110101110111010111111111011 ,
1%
#102
0%
#103
1)
1.
b11111101 "
b11111101 +
b10010110 !
b10010110 0
b1111111010111011101011111111101 $
b1111111010111011101011111111101 *
b1111111010111011101011111111101 ,
b110101000011001101010010010110 #
b110101000011001101010010010110 /
b110101000011001101010010010110 1
1%
#104
0%
#105
0.
0)
b1001011 !
b1001011 0
b11111110 "
b11111110 +
b10011010100001100110101001001011 #
b10011010100001100110101001001011 /
b10011010100001100110101001001011 1
b10111111101011101110101111111110 $
b10111111101011101110101111111110 *
b10111111101011101110101111111110 ,
1%
#106
0%
#107
1.
0)
b11111111 "
b11111111 +
b100101 !
b100101 0
b1011111110101110111010111111111 $
b1011111110101110111010111111111 *
b1011111110101110111010111111111 ,
b1001101010000110011010100100101 #
b1001101010000110011010100100101 /
b1001101010000110011010100100101 1
1%
#108
0%
#109
0)
1.
b10010010 !
b10010010 0
b10100110101000011001101010010010 #
b10100110101000011001101010010010 /
b10100110101000011001101010010010 1
b101111111010111011101011111111 $
b101111111010111011101011111111 *
b101111111010111011101011111111 ,
1%
#110
0%
#111
0)
0.
b1111111 "
b1111111 +
b1001001 !
b1001001 0
b10111111101011101110101111111 $
b10111111101011101110101111111 *
b10111111101011101110101111111 ,
b11010011010100001100110101001001 #
b11010011010100001100110101001001 /
b11010011010100001100110101001001 1
1%
#112
0%
#113
1)
1.
b10100100 !
b10100100 0
b10111111 "
b10111111 +
b1101001101010000110011010100100 #
b1101001101010000110011010100100 /
b1101001101010000110011010100100 1
b1011111110101110111010111111 $
b1011111110101110111010111111 *
b1011111110101110111010111111 ,
1%
#114
0%
#115
0.
0)
b1011111 "
b1011111 +
b1010010 !
b1010010 0
b10000101111111010111011101011111 $
b10000101111111010111011101011111 *
b10000101111111010111011101011111 ,
b10110100110101000011001101010010 #
b10110100110101000011001101010010 /
b10110100110101000011001101010010 1
1%
#116
0%
#117
1)
0.
b10101001 !
b10101001 0
b10101111 "
b10101111 +
b1011010011010100001100110101001 #
b1011010011010100001100110101001 /
b1011010011010100001100110101001 1
b1000010111111101011101110101111 $
b1000010111111101011101110101111 *
b1000010111111101011101110101111 ,
1%
#118
0%
#119
1)
0.
b11010111 "
b11010111 +
b11010100 !
b11010100 0
b10100001011111110101110111010111 $
b10100001011111110101110111010111 *
b10100001011111110101110111010111 ,
b101101001101010000110011010100 #
b101101001101010000110011010100 /
b101101001101010000110011010100 1
1%
#120
0%
#121
1)
1.
b1101010 !
b1101010 0
b11101011 "
b11101011 +
b10110100110101000011001101010 #
b10110100110101000011001101010 /
b10110100110101000011001101010 1
b11010000101111111010111011101011 $
b11010000101111111010111011101011 *
b11010000101111111010111011101011 ,
1%
#122
0%
#123
1)
0.
b1110101 "
b1110101 +
b110101 !
b110101 0
b11101000010111111101011101110101 $
b11101000010111111101011101110101 *
b11101000010111111101011101110101 ,
b10001011010011010100001100110101 #
b10001011010011010100001100110101 /
b10001011010011010100001100110101 1
1%
#124
0%
#125
1.
1)
b10011010 !
b10011010 0
b10111010 "
b10111010 +
b1000101101001101010000110011010 #
b1000101101001101010000110011010 /
b1000101101001101010000110011010 1
b11110100001011111110101110111010 $
b11110100001011111110101110111010 *
b11110100001011111110101110111010 ,
1%
