fsm/delay_ms.v
module DELAY_MS(rst, clk, enable, done, ms);

input wire rst, clk, enable;
output wire done;
input wire [31:0] ms;


localparam fclk = 5000;
localparam ms1 = fclk/1000;

reg [31:0] cnt_clk;
reg [31:0] cnt_ms;
reg done_r;

assign done = done_r;

always @(posedge rst or posedge clk)
begin
	if(rst)
	begin
		cnt_clk = 32'b0;
		cnt_ms = 3'b0;
		done_r = 0;
	end
	else if(clk)
	begin
		if(enable)
		begin
			cnt_clk <= cnt_clk + 1;
			if(cnt_clk >= ms1)
			begin
				cnt_ms = cnt_ms + 1;
				cnt_clk <= 0;
			end
			if(cnt_ms >= ms)
				done_r = 1;
		end
		else 
		begin
			cnt_clk = 32'b0;
			cnt_ms = 3'b0;
			done_r = 0;
		end
			
	end
end

endmodule

spi/reset.v
module RESET(rst,clk);

output rst;
input clk;

reg [3:0] count_rst = 4'h0;
reg rst;
always @ (posedge clk)
begin
	if (count_rst<=4'd10) begin
		rst<=1'b1;
		count_rst<=count_rst+1'b1; 
	end
	else begin
		rst<=1'b0;
		count_rst<=4'd15; 
	end
end

endmodule

fsm/main.v
module MAIN (clk);

input  wire clk;
	
wire rst;
RESET reset(.rst(rst),.clk(clk));

reg delay_enable;
wire delay_done;
reg [31:0] delay_time;
DELAY_MS delay_ms(.rst(rst),.clk(clk),.enable(delay_enable),.done(delay_done),.ms(delay_time));

reg led1_r, led2_r, led3_r;

reg [3:0] state;

always @(posedge rst or posedge clk)
begin
	if(rst)
	begin
		led1_r = 0; led2_r = 0; led3_r = 0; state = 0;
	end
	else if(clk)
	begin
		case(state)
		0:
		begin
			led1_r <= ~led1_r;
			state <= state + 1;
		end
		1:
		begin
			delay_time <= 10;
			delay_enable <= 1;
			if(delay_done)
			begin
				delay_enable <= 0;
				state <= state + 1;
			end
		end
		2:
		begin
			led2_r <= ~led2_r;
			state <= state + 1;
		end
		3:
		begin
			delay_time <= 10;
			delay_enable <= 1;
			if(delay_done)
			begin
				delay_enable <= 0;
				state <= state + 1;
			end
		end
		4:
		begin
			led3_r <= ~led3_r;
			state <= state + 1;
		end
		5:
		begin
			delay_time <= 10;
			delay_enable <= 1;
			if(delay_done)
			begin
				delay_enable <= 0;
				state <= state + 1;
			end
		end
		default:
			state <= 0;
		endcase
	end
end

endmodule

fsm/testbench.v
module testbench ();
  
reg clk;

MAIN main(.clk(clk));

initial
begin
	$dumpfile("out.vcd");
	$dumpvars(0,testbench);
	clk = 0;
end

always #1 clk = !clk;

initial
begin
	#10000 $finish;
end

endmodule

fsm/out.vcd
$date
	Mon Mar 19 10:34:53 2018
$end
$version
	Icarus Verilog
$end
$timescale
	1s
$end
$scope module testbench $end
$var reg 1 ! clk $end
$scope module main $end
$var wire 1 ! clk $end
$var wire 1 " rst $end
$var wire 1 # delay_done $end
$var reg 1 $ delay_enable $end
$var reg 32 % delay_time [31:0] $end
$var reg 1 & led1_r $end
$var reg 1 ' led2_r $end
$var reg 1 ( led3_r $end
$var reg 4 ) state [3:0] $end
$scope module delay_ms $end
$var wire 1 ! clk $end
$var wire 1 # done $end
$var wire 1 $ enable $end
$var wire 32 * ms [31:0] $end
$var wire 1 " rst $end
$var reg 32 + cnt_clk [31:0] $end
$var reg 32 , cnt_ms [31:0] $end
$var reg 1 - done_r $end
$upscope $end
$scope module reset $end
$var wire 1 ! clk $end
$var reg 4 . count_rst [3:0] $end
$var reg 1 " rst $end
$upscope $end
$upscope $end
$upscope $end
$enddefinitions $end
#0
$dumpvars
b0 .
x-
bx ,
bx +
bx *
bx )
x(
x'
x&
bx %
x$
x#
x"
0!
$end
#1
0(
0'
0&
b0 )
b1 .
1"
0#
0-
b0 ,
b0 +
1!
#2
0!
#3
b10 .
1!
#4
0!
#5
b11 .
1!
#6
0!
#7
b100 .
1!
#8
0!
#9
b101 .
1!
#10
0!
#11
b110 .
1!
#12
0!
#13
b111 .
1!
#14
0!
#15
b1000 .
1!
#16
0!
#17
b1001 .
1!
#18
0!
#19
b1010 .
1!
#20
0!
#21
b1011 .
1!
#22
0!
#23
b1111 .
0"
1!
#24
0!
#25
b1 )
1&
1!
#26
0!
#27
1$
b1010 %
b1010 *
1!
#28
0!
#29
b1 +
1!
#30
0!
#31
b10 +
1!
#32
0!
#33
b11 +
1!
#34
0!
#35
b100 +
1!
#36
0!
#37
b101 +
1!
#38
0!
#39
b0 +
b1 ,
1!
#40
0!
#41
b1 +
1!
#42
0!
#43
b10 +
1!
#44
0!
#45
b11 +
1!
#46
0!
#47
b100 +
1!
#48
0!
#49
b101 +
1!
#50
0!
#51
b0 +
b10 ,
1!
#52
0!
#53
b1 +
1!
#54
0!
#55
b10 +
1!
#56
0!
#57
b11 +
1!
#58
0!
#59
b100 +
1!
#60
0!
#61
b101 +
1!
#62
0!
#63
b0 +
b11 ,
1!
#64
0!
#65
b1 +
1!
#66
0!
#67
b10 +
1!
#68
0!
#69
b11 +
1!
#70
0!
#71
b100 +
1!
#72
0!
#73
b101 +
1!
#74
0!
#75
b0 +
b100 ,
1!
#76
0!
#77
b1 +
1!
#78
0!
#79
b10 +
1!
#80
0!
#81
b11 +
1!
#82
0!
#83
b100 +
1!
#84
0!
#85
b101 +
1!
#86
0!
#87
b0 +
b101 ,
1!
#88
0!
#89
b1 +
1!
#90
0!
#91
b10 +
1!
#92
0!
#93
b11 +
1!
#94
0!
#95
b100 +
1!
#96
0!
#97
b101 +
1!
#98
0!
#99
b0 +
b110 ,
1!
#100
0!
#101
b1 +
1!
#102
0!
#103
b10 +
1!
#104
0!
#105
b11 +
1!
#106
0!
#107
b100 +
1!
#108
0!
#109
b101 +
1!
#110
0!
#111
b0 +
b111 ,
1!
#112
0!
#113
b1 +
1!
#114
0!
#115
b10 +
1!
#116
0!
#117
b11 +
1!
#118
0!
#119
b100 +
1!
#120
0!
#121
b101 +
1!
#122
0!
#123
b0 +
b1000 ,
1!
#124
0!
#125
b1 +
1!
#126
0!
#127
b10 +
1!
#128
0!
#129
b11 +
1!
#130
0!
#131
b100 +
1!
#132
0!
#133
b101 +
1!
#134
0!
#135
b0 +
b1001 ,
1!
#136
0!
#137
b1 +
1!
#138
0!
#139
b10 +
1!
#140
0!
#141
b11 +
1!
#142
0!
#143
b100 +
1!
#144
0!
#145
b101 +
1!
#146
0!
#147
b0 +
1#
1-
b1010 ,
1!
#148
0!
#149
b10 )
0$
b1 +
1!
#150
0!
#151
b11 )
1'
0#
0-
b0 ,
b0 +
1!
#152
0!
#153
1$
1!
#154
0!
#155
b1 +
1!
#156
0!
#157
b10 +
1!
#158
0!
#159
b11 +
1!
#160
0!
#161
b100 +
1!
#162
0!
#163
b101 +
1!
#164
0!
#165
b0 +
b1 ,
1!
#166
0!
#167
b1 +
1!
#168
0!
#169
b10 +
1!
#170
0!
#171
b11 +
1!
#172
0!
#173
b100 +
1!
#174
0!
#175
b101 +
1!
#176
0!
#177
b0 +
b10 ,
1!
#178
0!
#179
b1 +
1!
#180
0!
#181
b10 +
1!
#182
0!
#183
b11 +
1!
#184
0!
#185
b100 +
1!
#186
0!
#187
b101 +
1!
#188
0!
#189
b0 +
b11 ,
1!
#190
0!
#191
b1 +
1!
#192
0!
#193
b10 +
1!
#194
0!
#195
b11 +
1!
#196
0!
#197
b100 +
1!
#198
0!
#199
b101 +
1!
#200
0!
#201
b0 +
b100 ,
1!
#202
0!
#203
b1 +
1!
#204
0!
#205
b10 +
1!
#206
0!
#207
b11 +
1!
#208
0!
#209
b100 +
1!
#210
0!
#211
b101 +
1!
#212
0!
#213
b0 +
b101 ,
1!
#214
0!
#215
b1 +
1!
#216
0!
#217
b10 +
1!
#218
0!
#219
b11 +
1!
#220
0!
#221
b100 +
1!
#222
0!
#223
b101 +
1!
#224
0!
#225
b0 +
b110 ,
1!
#226
0!
#227
b1 +
1!
#228
0!
#229
b10 +
1!
#230
0!
#231
b11 +
1!
#232
0!
#233
b100 +
1!
#234
0!
#235
b101 +
1!
#236
0!
#237
b0 +
b111 ,
1!
#238
0!
#239
b1 +
1!
#240
0!
#241
b10 +
1!
#242
0!
#243
b11 +
1!
#244
0!
#245
b100 +
1!
#246
0!
#247
b101 +
1!
#248
0!
#249
b0 +
b1000 ,
1!
#250
0!
#251
b1 +
1!
#252
0!
#253
b10 +
1!
#254
0!
#255
b11 +
1!
#256
0!
#257
b100 +
1!
#258
0!
#259
b101 +
1!
#260
0!
#261
b0 +
b1001 ,
1!
#262
0!
#263
b1 +
1!
#264
0!
#265
b10 +
1!
#266
0!
#267
b11 +
1!
#268
0!
#269
b100 +
1!
#270
0!
#271
b101 +
1!
#272
0!
#273
b100 )
0$
b0 +
1#
1-
b1010 ,
1!
#274
0!
#275
b101 )
1(
0#
0-
b0 ,
1!
#276
0!
#277
1$
1!
#278
0!
#279
b1 +
1!
#280
0!
#281
b10 +
1!
#282
0!
#283
b11 +
1!
#284
0!
#285
b100 +
1!
#286
0!
#287
b101 +
1!
#288
0!
#289
b0 +
b1 ,
1!
#290
0!
#291
b1 +
1!
#292
0!
#293
b10 +
1!
#294
0!
#295
b11 +
1!
#296
0!
#297
b100 +
1!
#298
0!
#299
b101 +
1!
#300
0!
#301
b0 +
b10 ,
1!
#302
0!
#303
b1 +
1!
#304
0!
#305
b10 +
1!
#306
0!
#307
b11 +
1!
#308
0!
#309
b100 +
1!
#310
0!
#311
b101 +
1!
#312
0!
#313
b0 +
b11 ,
1!
#314
0!
#315
b1 +
1!
#316
0!
#317
b10 +
1!
#318
0!
#319
b11 +
1!
#320
0!
#321
b100 +
1!
#322
0!
#323
b101 +
1!
#324
0!
#325
b0 +
b100 ,
1!
#326
0!
#327
b1 +
1!
#328
0!
#329
b10 +
1!
#330
0!
#331
b11 +
1!
#332
0!
#333
b100 +
1!
#334
0!
#335
b101 +
1!
#336
0!
#337
b0 +
b101 ,
1!
#338
0!
#339
b1 +
1!
#340
0!
#341
b10 +
1!
#342
0!
#343
b11 +
1!
#344
0!
#345
b100 +
1!
#346
0!
#347
b101 +
1!
#348
0!
#349
b0 +
b110 ,
1!
#350
0!
#351
b1 +
1!
#352
0!
#353
b10 +
1!
#354
0!
#355
b11 +
1!
#356
0!
#357
b100 +
1!
#358
0!
#359
b101 +
1!
#360
0!
#361
b0 +
b111 ,
1!
#362
0!
#363
b1 +
1!
#364
0!
#365
b10 +
1!
#366
0!
#367
b11 +
1!
#368
0!
#369
b100 +
1!
#370
0!
#371
b101 +
1!
#372
0!
#373
b0 +
b1000 ,
1!
#374
0!
#375
b1 +
1!
#376
0!
#377
b10 +
1!
#378
0!
#379
b11 +
1!
#380
0!
#381
b100 +
1!
#382
0!
#383
b101 +
1!
#384
0!
#385
b0 +
b1001 ,
1!
#386
0!
#387
b1 +
1!
#388
0!
#389
b10 +
1!
#390
0!
#391
b11 +
1!
#392
0!
#393
b100 +
1!
#394
0!
#395
b101 +
1!
#396
0!
#397
b0 )
0$
b0 +
1#
1-
b1010 ,
1!
#398
0!
#399
b1 )
0&
0#
0-
b0 ,
1!
#400
0!
#401
1$
1!
#402
0!
#403
b1 +
1!
#404
0!
#405
b10 +
1!
#406
0!
#407
b11 +
1!
#408
0!
#409
b100 +
1!
#410
0!
#411
b101 +
1!
#412
0!
#413
b0 +
b1 ,
1!
#414
0!
#415
b1 +
1!
#416
0!
#417
b10 +
1!
#418
0!
#419
b11 +
1!
#420
0!
#421
b100 +
1!
#422
0!
#423
b101 +
1!
#424
0!
#425
b0 +
b10 ,
1!
#426
0!
#427
b1 +
1!
#428
0!
#429
b10 +
1!
#430
0!
#431
b11 +
1!
#432
0!
#433
b100 +
1!
#434
0!
#435
b101 +
1!
#436
0!
#437
b0 +
b11 ,
1!
#438
0!
#439
b1 +
1!
#440
0!
#441
b10 +
1!
#442
0!
#443
b11 +
1!
#444
0!
#445
b100 +
1!
#446
0!
#447
b101 +
1!
#448
0!
#449
b0 +
b100 ,
1!
#450
0!
#451
b1 +
1!
#452
0!
#453
b10 +
1!
#454
0!
#455
b11 +
1!
#456
0!
#457
b100 +
1!
#458
0!
#459
b101 +
1!
#460
0!
#461
b0 +
b101 ,
1!
#462
0!
#463
b1 +
1!
#464
0!
#465
b10 +
1!
#466
0!
#467
b11 +
1!
#468
0!
#469
b100 +
1!
#470
0!
#471
b101 +
1!
#472
0!
#473
b0 +
b110 ,
1!
#474
0!
#475
b1 +
1!
#476
0!
#477
b10 +
1!
#478
0!
#479
b11 +
1!
#480
0!
#481
b100 +
1!
#482
0!
#483
b101 +
1!
#484
0!
#485
b0 +
b111 ,
1!
#486
0!
#487
b1 +
1!
#488
0!
#489
b10 +
1!
#490
0!
#491
b11 +
1!
#492
0!
#493
b100 +
1!
#494
0!
#495
b101 +
1!
#496
0!
#497
b0 +
b1000 ,
1!
#498
0!
#499
b1 +
1!
#500
0!
#501
b10 +
1!
#502
0!
#503
b11 +
1!
#504
0!
#505
b100 +
1!
#506
0!
#507
b101 +
1!
#508
0!
#509
b0 +
b1001 ,
1!
#510
0!
#511
b1 +
1!
#512
0!
#513
b10 +
1!
#514
0!
#515
b11 +
1!
#516
0!
#517
b100 +
1!
#518
0!
#519
b101 +
1!
#520
0!
#521
b10 )
0$
b0 +
1#
1-
b1010 ,
1!
#522
0!
#523
b11 )
0'
0#
0-
b0 ,
1!
#524
0!
#525
1$
1!
#526
0!
#527
b1 +
1!
#528
0!
#529
b10 +
1!
#530
0!
#531
b11 +
1!
#532
0!
#533
b100 +
1!
#534
0!
#535
b101 +
1!
#536
0!
#537
b0 +
b1 ,
1!
#538
0!
#539
b1 +
1!
#540
0!
#541
b10 +
1!
#542
0!
#543
b11 +
1!
#544
0!
#545
b100 +
1!
#546
0!
#547
b101 +
1!
#548
0!
#549
b0 +
b10 ,
1!
#550
0!
#551
b1 +
1!
#552
0!
#553
b10 +
1!
#554
0!
#555
b11 +
1!
#556
0!
#557
b100 +
1!
#558
0!
#559
b101 +
1!
#560
0!
#561
b0 +
b11 ,
1!
#562
0!
#563
b1 +
1!
#564
0!
#565
b10 +
1!
#566
0!
#567
b11 +
1!
#568
0!
#569
b100 +
1!
#570
0!
#571
b101 +
1!
#572
0!
#573
b0 +
b100 ,
1!
#574
0!
#575
b1 +
1!
#576
0!
#577
b10 +
1!
#578
0!
#579
b11 +
1!
#580
0!
#581
b100 +
1!
#582
0!
#583
b101 +
1!
#584
0!
#585
b0 +
b101 ,
1!
#586
0!
#587
b1 +
1!
#588
0!
#589
b10 +
1!
#590
0!
#591
b11 +
1!
#592
0!
#593
b100 +
1!
#594
0!
#595
b101 +
1!
#596
0!
#597
b0 +
b110 ,
1!
#598
0!
#599
b1 +
1!
#600
0!
#601
b10 +
1!
#602
0!
#603
b11 +
1!
#604
0!
#605
b100 +
1!
#606
0!
#607
b101 +
1!
#608
0!
#609
b0 +
b111 ,
1!
#610
0!
#611
b1 +
1!
#612
0!
#613
b10 +
1!
#614
0!
#615
b11 +
1!
#616
0!
#617
b100 +
1!
#618
0!
#619
b101 +
1!
#620
0!
#621
b0 +
b1000 ,
1!
#622
0!
#623
b1 +
1!
#624
0!
#625
b10 +
1!
#626
0!
#627
b11 +
1!
#628
0!
#629
b100 +
1!
#630
0!
#631
b101 +
1!
#632
0!
#633
b0 +
b1001 ,
1!
#634
0!
#635
b1 +
1!
#636
0!
#637
b10 +
1!
#638
0!
#639
b11 +
1!
#640
0!
#641
b100 +
1!
#642
0!
#643
b101 +
1!
#644
0!
#645
b100 )
0$
b0 +
1#
1-
b1010 ,
1!
#646
0!
#647
b101 )
0(
0#
0-
b0 ,
1!
#648
0!
#649
1$
1!
#650
0!
#651
b1 +
1!
#652
0!
#653
b10 +
1!
#654
0!
#655
b11 +
1!
#656
0!
#657
b100 +
1!
#658
0!
#659
b101 +
1!
#660
0!
#661
b0 +
b1 ,
1!
#662
0!
#663
b1 +
1!
#664
0!
#665
b10 +
1!
#666
0!
#667
b11 +
1!
#668
0!
#669
b100 +
1!
#670
0!
#671
b101 +
1!
#672
0!
#673
b0 +
b10 ,
1!
#674
0!
#675
b1 +
1!
#676
0!
#677
b10 +
1!
#678
0!
#679
b11 +
1!
#680
0!
#681
b100 +
1!
#682
0!
#683
b101 +
1!
#684
0!
#685
b0 +
b11 ,
1!
#686
0!
#687
b1 +
1!
#688
0!
#689
b10 +
1!
#690
0!
#691
b11 +
1!
#692
0!
#693
b100 +
1!
#694
0!
#695
b101 +
1!
#696
0!
#697
b0 +
b100 ,
1!
#698
0!
#699
b1 +
1!
#700
0!
#701
b10 +
1!
#702
0!
#703
b11 +
1!
#704
0!
#705
b100 +
1!
#706
0!
#707
b101 +
1!
#708
0!
#709
b0 +
b101 ,
1!
#710
0!
#711
b1 +
1!
#712
0!
#713
b10 +
1!
#714
0!
#715
b11 +
1!
#716
0!
#717
b100 +
1!
#718
0!
#719
b101 +
1!
#720
0!
#721
b0 +
b110 ,
1!
#722
0!
#723
b1 +
1!
#724
0!
#725
b10 +
1!
#726
0!
#727
b11 +
1!
#728
0!
#729
b100 +
1!
#730
0!
#731
b101 +
1!
#732
0!
#733
b0 +
b111 ,
1!
#734
0!
#735
b1 +
1!
#736
0!
#737
b10 +
1!
#738
0!
#739
b11 +
1!
#740
0!
#741
b100 +
1!
#742
0!
#743
b101 +
1!
#744
0!
#745
b0 +
b1000 ,
1!
#746
0!
#747
b1 +
1!
#748
0!
#749
b10 +
1!
#750
0!
#751
b11 +
1!
#752
0!
#753
b100 +
1!
#754
0!
#755
b101 +
1!
#756
0!
#757
b0 +
b1001 ,
1!
#758
0!
#759
b1 +
1!
#760
0!
#761
b10 +
1!
#762
0!
#763
b11 +
1!
#764
0!
#765
b100 +
1!
#766
0!
#767
b101 +
1!
#768
0!
#769
b0 )
0$
b0 +
1#
1-
b1010 ,
1!
#770
0!
#771
b1 )
1&
0#
0-
b0 ,
1!
#772
0!
#773
1$
1!
#774
0!
#775
b1 +
1!
#776
0!
#777
b10 +
1!
#778
0!
#779
b11 +
1!
#780
0!
#781
b100 +
1!
#782
0!
#783
b101 +
1!
#784
0!
#785
b0 +
b1 ,
1!
#786
0!
#787
b1 +
1!
#788
0!
#789
b10 +
1!
#790
0!
#791
b11 +
1!
#792
0!
#793
b100 +
1!
#794
0!
#795
b101 +
1!
#796
0!
#797
b0 +
b10 ,
1!
#798
0!
#799
b1 +
1!
#800
0!
#801
b10 +
1!
#802
0!
#803
b11 +
1!
#804
0!
#805
b100 +
1!
#806
0!
#807
b101 +
1!
#808
0!
#809
b0 +
b11 ,
1!
#810
0!
#811
b1 +
1!
#812
0!
#813
b10 +
1!
#814
0!
#815
b11 +
1!
#816
0!
#817
b100 +
1!
#818
0!
#819
b101 +
1!
#820
0!
#821
b0 +
b100 ,
1!
#822
0!
#823
b1 +
1!
#824
0!
#825
b10 +
1!
#826
0!
#827
b11 +
1!
#828
0!
#829
b100 +
1!
#830
0!
#831
b101 +
1!
#832
0!
#833
b0 +
b101 ,
1!
#834
0!
#835
b1 +
1!
#836
0!
#837
b10 +
1!
#838
0!
#839
b11 +
1!
#840
0!
#841
b100 +
1!
#842
0!
#843
b101 +
1!
#844
0!
#845
b0 +
b110 ,
1!
#846
0!
#847
b1 +
1!
#848
0!
#849
b10 +
1!
#850
0!
#851
b11 +
1!
#852
0!
#853
b100 +
1!
#854
0!
#855
b101 +
1!
#856
0!
#857
b0 +
b111 ,
1!
#858
0!
#859
b1 +
1!
#860
0!
#861
b10 +
1!
#862
0!
#863
b11 +
1!
#864
0!
#865
b100 +
1!
#866
0!
#867
b101 +
1!
#868
0!
#869
b0 +
b1000 ,
1!
#870
0!
#871
b1 +
1!
#872
0!
#873
b10 +
1!
#874
0!
#875
b11 +
1!
#876
0!
#877
b100 +
1!
#878
0!
#879
b101 +
1!
#880
0!
#881
b0 +
b1001 ,
1!
#882
0!
#883
b1 +
1!
#884
0!
#885
b10 +
1!
#886
0!
#887
b11 +
1!
#888
0!
#889
b100 +
1!
#890
0!
#891
b101 +
1!
#892
0!
#893
b10 )
0$
b0 +
1#
1-
b1010 ,
1!
#894
0!
#895
b11 )
1'
0#
0-
b0 ,
1!
#896
0!
#897
1$
1!
#898
0!
#899
b1 +
1!
#900
0!
#901
b10 +
1!
#902
0!
#903
b11 +
1!
#904
0!
#905
b100 +
1!
#906
0!
#907
b101 +
1!
#908
0!
#909
b0 +
b1 ,
1!
#910
0!
#911
b1 +
1!
#912
0!
#913
b10 +
1!
#914
0!
#915
b11 +
1!
#916
0!
#917
b100 +
1!
#918
0!
#919
b101 +
1!
#920
0!
#921
b0 +
b10 ,
1!
#922
0!
#923
b1 +
1!
#924
0!
#925
b10 +
1!
#926
0!
#927
b11 +
1!
#928
0!
#929
b100 +
1!
#930
0!
#931
b101 +
1!
#932
0!
#933
b0 +
b11 ,
1!
#934
0!
#935
b1 +
1!
#936
0!
#937
b10 +
1!
#938
0!
#939
b11 +
1!
#940
0!
#941
b100 +
1!
#942
0!
#943
b101 +
1!
#944
0!
#945
b0 +
b100 ,
1!
#946
0!
#947
b1 +
1!
#948
0!
#949
b10 +
1!
#950
0!
#951
b11 +
1!
#952
0!
#953
b100 +
1!
#954
0!
#955
b101 +
1!
#956
0!
#957
b0 +
b101 ,
1!
#958
0!
#959
b1 +
1!
#960
0!
#961
b10 +
1!
#962
0!
#963
b11 +
1!
#964
0!
#965
b100 +
1!
#966
0!
#967
b101 +
1!
#968
0!
#969
b0 +
b110 ,
1!
#970
0!
#971
b1 +
1!
#972
0!
#973
b10 +
1!
#974
0!
#975
b11 +
1!
#976
0!
#977
b100 +
1!
#978
0!
#979
b101 +
1!
#980
0!
#981
b0 +
b111 ,
1!
#982
0!
#983
b1 +
1!
#984
0!
#985
b10 +
1!
#986
0!
#987
b11 +
1!
#988
0!
#989
b100 +
1!
#990
0!
#991
b101 +
1!
#992
0!
#993
b0 +
b1000 ,
1!
#994
0!
#995
b1 +
1!
#996
0!
#997
b10 +
1!
#998
0!
#999
b11 +
1!
#1000
0!
#1001
b100 +
1!
#1002
0!
#1003
b101 +
1!
#1004
0!
#1005
b0 +
b1001 ,
1!
#1006
0!
#1007
b1 +
1!
#1008
0!
#1009
b10 +
1!
#1010
0!
#1011
b11 +
1!
#1012
0!
#1013
b100 +
1!
#1014
0!
#1015
b101 +
1!
#1016
0!
#1017
b100 )
0$
b0 +
1#
1-
b1010 ,
1!
#1018
0!
#1019
b101 )
1(
0#
0-
b0 ,
1!
#1020
0!
#1021
1$
1!
#1022
0!
#1023
b1 +
1!
#1024
0!
#1025
b10 +
1!
#1026
0!
#1027
b11 +
1!
#1028
0!
#1029
b100 +
1!
#1030
0!
#1031
b101 +
1!
#1032
0!
#1033
b0 +
b1 ,
1!
#1034
0!
#1035
b1 +
1!
#1036
0!
#1037
b10 +
1!
#1038
0!
#1039
b11 +
1!
#1040
0!
#1041
b100 +
1!
#1042
0!
#1043
b101 +
1!
#1044
0!
#1045
b0 +
b10 ,
1!
#1046
0!
#1047
b1 +
1!
#1048
0!
#1049
b10 +
1!
#1050
0!
#1051
b11 +
1!
#1052
0!
#1053
b100 +
1!
#1054
0!
#1055
b101 +
1!
#1056
0!
#1057
b0 +
b11 ,
1!
#1058
0!
#1059
b1 +
1!
#1060
0!
#1061
b10 +
1!
#1062
0!
#1063
b11 +
1!
#1064
0!
#1065
b100 +
1!
#1066
0!
#1067
b101 +
1!
#1068
0!
#1069
b0 +
b100 ,
1!
#1070
0!
#1071
b1 +
1!
#1072
0!
#1073
b10 +
1!
#1074
0!
#1075
b11 +
1!
#1076
0!
#1077
b100 +
1!
#1078
0!
#1079
b101 +
1!
#1080
0!
#1081
b0 +
b101 ,
1!
#1082
0!
#1083
b1 +
1!
#1084
0!
#1085
b10 +
1!
#1086
0!
#1087
b11 +
1!
#1088
0!
#1089
b100 +
1!
#1090
0!
#1091
b101 +
1!
#1092
0!
#1093
b0 +
b110 ,
1!
#1094
0!
#1095
b1 +
1!
#1096
0!
#1097
b10 +
1!
#1098
0!
#1099
b11 +
1!
#1100
0!
#1101
b100 +
1!
#1102
0!
#1103
b101 +
1!
#1104
0!
#1105
b0 +
b111 ,
1!
#1106
0!
#1107
b1 +
1!
#1108
0!
#1109
b10 +
1!
#1110
0!
#1111
b11 +
1!
#1112
0!
#1113
b100 +
1!
#1114
0!
#1115
b101 +
1!
#1116
0!
#1117
b0 +
b1000 ,
1!
#1118
0!
#1119
b1 +
1!
#1120
0!
#1121
b10 +
1!
#1122
0!
#1123
b11 +
1!
#1124
0!
#1125
b100 +
1!
#1126
0!
#1127
b101 +
1!
#1128
0!
#1129
b0 +
b1001 ,
1!
#1130
0!
#1131
b1 +
1!
#1132
0!
#1133
b10 +
1!
#1134
0!
#1135
b11 +
1!
#1136
0!
#1137
b100 +
1!
#1138
0!
#1139
b101 +
1!
#1140
0!
#1141
b0 )
0$
b0 +
1#
1-
b1010 ,
1!
#1142
0!
#1143
b1 )
0&
0#
0-
b0 ,
1!
#1144
0!
#1145
1$
1!
#1146
0!
#1147
b1 +
1!
#1148
0!
#1149
b10 +
1!
#1150
0!
#1151
b11 +
1!
#1152
0!
#1153
b100 +
1!
#1154
0!
#1155
b101 +
1!
#1156
0!
#1157
b0 +
b1 ,
1!
#1158
0!
#1159
b1 +
1!
#1160
0!
#1161
b10 +
1!
#1162
0!
#1163
b11 +
1!
#1164
0!
#1165
b100 +
1!
#1166
0!
#1167
b101 +
1!
#1168
0!
#1169
b0 +
b10 ,
1!
#1170
0!
#1171
b1 +
1!
#1172
0!
#1173
b10 +
1!
#1174
0!
#1175
b11 +
1!
#1176
0!
#1177
b100 +
1!
#1178
0!
#1179
b101 +
1!
#1180
0!
#1181
b0 +
b11 ,
1!
#1182
0!
#1183
b1 +
1!
#1184
0!
#1185
b10 +
1!
#1186
0!
#1187
b11 +
1!
#1188
0!
#1189
b100 +
1!
#1190
0!
#1191
b101 +
1!
#1192
0!
#1193
b0 +
b100 ,
1!
#1194
0!
#1195
b1 +
1!
#1196
0!
#1197
b10 +
1!
#1198
0!
#1199
b11 +
1!
#1200
0!
#1201
b100 +
1!
#1202
0!
#1203
b101 +
1!
#1204
0!
#1205
b0 +
b101 ,
1!
#1206
0!
#1207
b1 +
1!
#1208
0!
#1209
b10 +
1!
#1210
0!
#1211
b11 +
1!
#1212
0!
#1213
b100 +
1!
#1214
0!
#1215
b101 +
1!
#1216
0!
#1217
b0 +
b110 ,
1!
#1218
0!
#1219
b1 +
1!
#1220
0!
#1221
b10 +
1!
#1222
0!
#1223
b11 +
1!
#1224
0!
#1225
b100 +
1!
#1226
0!
#1227
b101 +
1!
#1228
0!
#1229
b0 +
b111 ,
1!
#1230
0!
#1231
b1 +
1!
#1232
0!
#1233
b10 +
1!
#1234
0!
#1235
b11 +
1!
#1236
0!
#1237
b100 +
1!
#1238
0!
#1239
b101 +
1!
#1240
0!
#1241
b0 +
b1000 ,
1!
#1242
0!
#1243
b1 +
1!
#1244
0!
#1245
b10 +
1!
#1246
0!
#1247
b11 +
1!
#1248
0!
#1249
b100 +
1!
#1250
0!
#1251
b101 +
1!
#1252
0!
#1253
b0 +
b1001 ,
1!
#1254
0!
#1255
b1 +
1!
#1256
0!
#1257
b10 +
1!
#1258
0!
#1259
b11 +
1!
#1260
0!
#1261
b100 +
1!
#1262
0!
#1263
b101 +
1!
#1264
0!
#1265
b10 )
0$
b0 +
1#
1-
b1010 ,
1!
#1266
0!
#1267
b11 )
0'
0#
0-
b0 ,
1!
#1268
0!
#1269
1$
1!
#1270
0!
#1271
b1 +
1!
#1272
0!
#1273
b10 +
1!
#1274
0!
#1275
b11 +
1!
#1276
0!
#1277
b100 +
1!
#1278
0!
#1279
b101 +
1!
#1280
0!
#1281
b0 +
b1 ,
1!
#1282
0!
#1283
b1 +
1!
#1284
0!
#1285
b10 +
1!
#1286
0!
#1287
b11 +
1!
#1288
0!
#1289
b100 +
1!
#1290
0!
#1291
b101 +
1!
#1292
0!
#1293
b0 +
b10 ,
1!
#1294
0!
#1295
b1 +
1!
#1296
0!
#1297
b10 +
1!
#1298
0!
#1299
b11 +
1!
#1300
0!
#1301
b100 +
1!
#1302
0!
#1303
b101 +
1!
#1304
0!
#1305
b0 +
b11 ,
1!
#1306
0!
#1307
b1 +
1!
#1308
0!
#1309
b10 +
1!
#1310
0!
#1311
b11 +
1!
#1312
0!
#1313
b100 +
1!
#1314
0!
#1315
b101 +
1!
#1316
0!
#1317
b0 +
b100 ,
1!
#1318
0!
#1319
b1 +
1!
#1320
0!
#1321
b10 +
1!
#1322
0!
#1323
b11 +
1!
#1324
0!
#1325
b100 +
1!
#1326
0!
#1327
b101 +
1!
#1328
0!
#1329
b0 +
b101 ,
1!
#1330
0!
#1331
b1 +
1!
#1332
0!
#1333
b10 +
1!
#1334
0!
#1335
b11 +
1!
#1336
0!
#1337
b100 +
1!
#1338
0!
#1339
b101 +
1!
#1340
0!
#1341
b0 +
b110 ,
1!
#1342
0!
#1343
b1 +
1!
#1344
0!
#1345
b10 +
1!
#1346
0!
#1347
b11 +
1!
#1348
0!
#1349
b100 +
1!
#1350
0!
#1351
b101 +
1!
#1352
0!
#1353
b0 +
b111 ,
1!
#1354
0!
#1355
b1 +
1!
#1356
0!
#1357
b10 +
1!
#1358
0!
#1359
b11 +
1!
#1360
0!
#1361
b100 +
1!
#1362
0!
#1363
b101 +
1!
#1364
0!
#1365
b0 +
b1000 ,
1!
#1366
0!
#1367
b1 +
1!
#1368
0!
#1369
b10 +
1!
#1370
0!
#1371
b11 +
1!
#1372
0!
#1373
b100 +
1!
#1374
0!
#1375
b101 +
1!
#1376
0!
#1377
b0 +
b1001 ,
1!
#1378
0!
#1379
b1 +
1!
#1380
0!
#1381
b10 +
1!
#1382
0!
#1383
b11 +
1!
#1384
0!
#1385
b100 +
1!
